TSPLifesaver/__init__.py
TSPLifesaver/optimizer.py
TSPLifesaver/structure.py
TSPLifesaver/tools.py
TSPLifesaver/abc/__init__.py
TSPLifesaver/abc/abc.py
TSPLifesaver-0.0.3.dist-info/LICENSE
TSPLifesaver-0.0.3.dist-info/METADATA
TSPLifesaver-0.0.3.dist-info/WHEEL
TSPLifesaver-0.0.3.dist-info/top_level.txt
TSPLifesaver-0.0.3.dist-info/RECORD
