Metadata-Version: 2.1
Name: TSPLifesaver
Version: 0.0.3
Summary: A toolset that simplifies the process of solving TSP (Traveling Salesman Problem) problems. 
Author-email: Christian Lee <chrisliyuhan@gmail.com>
License: Copyright (c) 2023 Christian Lee
Project-URL: repository, https://github.com/lxbme/TSPLifesaver
Requires-Python: >=3.6
License-File: LICENSE
